{
	"set": {
		"tag": "oatsAndBeans",
		"name": {
			"en": "Oats and Beans",
			"fr": "Les plantes",
			"ru": "Растении"
		},
		"icon": {
			"src": "/Assets/Show/OatsAndBeans/icon.jpg"
		},
		"path": "/Show/OatsAndBeans",
		"parent": "/Show",
		"_id": "yfT8fZPHwRRbrQ3ws"
	},
	"phrases": [
		{
			"name": "splash",
			"menu": "exclude-from-menu",
			"image": [
				{
					"src": "/Assets/Show/OatsAndBeans/image/splash.jpg",
					"size": 98398
				}
			],
			"layout": "splash",
			"text": "25 September 2020\nJames Newton at\n[English Language Evenings III Moscow](http://elemoscow.net/location.html)",
			"tags": [
				"oatsAndBeans"
			],
			"tweak": {
				"background-color": "#fff",
				"color": "#000"
			},
			"_id": "4pT9midTF7Dvjo5rY"
		},
		{
			"name": "grass",
			"menu": {
				"en": "Watching Grass Grow",
				"fr": "Regarder pousser de l'herbe",
				"ru": "Cмотреть, как растет трава"
			},
			"layout": "video",
			"videoId": "rtFs6weCsHI",
			"width": 1472,
			"height": 974,
			"tags": [
				"oatsAndBeans"
			],
			"_id": "9kL6jhd4w54SfoR2H"
		},
		{
			"name": "earth",
			"menu": {
				"en": "The Age of the Earth",
				"fr": "L'âge de la terre",
				"ru": "Возраст земли"
			},
			"image": [
				{
					"src": "/Assets/Show/OatsAndBeans/image/earth.svg",
					"size": 57631
				}
			],
			"layout": "solo",
			"tweak": {
				"background-color": "#fff",
				"color": "#000"
			},
			"tags": [
				"oatsAndBeans"
			],
			"_id": "iGsYEexQuLXPuEKEE"
		},
		{
			"name": "first_plants",
			"menu": {
				"en": "The First Plants on Dry Land",
				"fr": "Les premières plantes sur la terre",
				"ru": "Первые растения на суше"
			},
			"image": [
				{
					"src": "/Assets/Show/OatsAndBeans/image/first_plants.jpg",
					"size": 196747
				}
			],
			"layout": "solo",
			"legend": [
				{
					"id": "first_plants",
					"en": "Liverwort (A, B, C), moss (D) and hornwort (E)",
					"fr": "Hépatiques (A, B, C), mousse (D) et anthocérote (E)",
					"ru": "Печёночные мхи (A, B, C), мох (D) и антоцеротовидные (E)"
				}
			],
			"tags": [
				"oatsAndBeans"
			],
			"_id": "dGRe2HrQ5TbYfasDe"
		}
	]
}